tex2svg/__init__.py
tex2svg-0.0.2.data/scripts/tex2svg
tex2svg-0.0.2.dist-info/COPYING
tex2svg-0.0.2.dist-info/LICENSE
tex2svg-0.0.2.dist-info/METADATA
tex2svg-0.0.2.dist-info/WHEEL
tex2svg-0.0.2.dist-info/top_level.txt
tex2svg-0.0.2.dist-info/RECORD
