Metadata-Version: 2.1
Name: tex2svg
Version: 0.0.2
Summary: A script to convert LaTeX snippets to SVG
Home-page: https://github.com/RyanMarcus/tex2svg
Author: Ryan Marcus
Author-email: ryan@ryanmarc.us
Classifier: Programming Language :: Python :: 3
Classifier: License :: OSI Approved :: GNU General Public License v3 or later (GPLv3+)
Classifier: Operating System :: OS Independent
License-File: LICENSE
License-File: COPYING
